datalines/__init__.py
datalines/dataloaders/__init__.py
datalines/dataloaders/BSDS500/BSDS500.py
datalines/dataloaders/BSDS500/__init__.py
datalines/dataloaders/BSDS500/def_load_dataset.py
datalines/dataloaders/BSDS500/res/BSDS_val68_list.txt
datalines-0.1.0.dist-info/LICENSE
datalines-0.1.0.dist-info/METADATA
datalines-0.1.0.dist-info/WHEEL
datalines-0.1.0.dist-info/top_level.txt
datalines-0.1.0.dist-info/RECORD
