Metadata-Version: 2.1
Name: datalines
Version: 0.1.0
Summary: Datalines = Dataloaders + Pipelines, add simplicity
Home-page: https://github.com/TheProjectsGuy/DataLines
Author: TheProjectsGuy
Author-email: vdd29rjre@mozmail.com
License: UNKNOWN
Project-URL: Bug Tracker, https://github.com/TheProjectsGuy/DataLines/issues
Platform: UNKNOWN
Classifier: Programming Language :: Python :: 3
Classifier: License :: OSI Approved :: GNU Lesser General Public License v3 or later (LGPLv3+)
Classifier: Operating System :: OS Independent
Requires-Python: >=3.6
License-File: LICENSE
